dsu/__init__.py
dsu/data_augmentation/__init__.py
dsu/data_augmentation/cv/__init__.py
dsu/data_augmentation/cv/flip_translate.py
dsu/data_augmentation/cv/random_crop.py
dsu/data_manipulation/__init__.py
dsu/data_manipulation/manipulation_tools.py
dsu/data_visualization/__init__.py
dsu/data_visualization/plotting_tools.py
datasu-0.1.1.dist-info/LICENSE
datasu-0.1.1.dist-info/METADATA
datasu-0.1.1.dist-info/WHEEL
datasu-0.1.1.dist-info/top_level.txt
datasu-0.1.1.dist-info/RECORD
