Metadata-Version: 2.1
Name: datasu
Version: 0.1.1
Summary: Essential utilities for data scientists
Home-page: https://github.com/danibcorr/data-scientist-utilities
Author: danibcorr (Daniel Bazo)
Keywords: python,data science,machine learning,deep learning,artificial intelligence
Classifier: Development Status :: 1 - Planning
Classifier: Intended Audience :: Developers
Classifier: Programming Language :: Python :: 3
Classifier: Operating System :: OS Independent
Classifier: License :: OSI Approved :: MIT License
Classifier: Topic :: Software Development :: Libraries :: Python Modules
License-File: LICENSE
Requires-Dist: numpy
Requires-Dist: numba
Requires-Dist: ipywidgets
Requires-Dist: matplotlib
Requires-Dist: seaborn
Requires-Dist: pandas
Requires-Dist: scikit-learn
